pymiaopai/__init__.py
pymiaopai/main.py
pymiaopai-2017.3.9.data/scripts/pymiaopai_cli
pymiaopai-2017.3.9.dist-info/DESCRIPTION.rst
pymiaopai-2017.3.9.dist-info/METADATA
pymiaopai-2017.3.9.dist-info/RECORD
pymiaopai-2017.3.9.dist-info/WHEEL
pymiaopai-2017.3.9.dist-info/metadata.json
pymiaopai-2017.3.9.dist-info/top_level.txt
