Metadata-Version: 2.0
Name: pymiaopai
Version: 2017.3.9
Summary: A python library for downloading miao pai vidoe.
Home-page: https://github.com/litton/MiaoPaiVideo
Author: fanlt
Author-email: litton.van@gmail.com
License: APACHE
Keywords: miaopai
Platform: UNKNOWN
